<?xml version="1.0"?>
<transmission>
    <reports>
        <report>
            <R4>kissa4</R4>
            <R5>2</R5>
            <R6>3</R6>
            <R7>4</R7>
            <R8>5</R8>
            <R9></R9>
        </report>
        <report>
            <R4>1</R4>
            <R5>2</R5>
            <R6>3</R6>
            <R7>4</R7>
            <R8>5</R8>
            <R9></R9>
        </report>
        <report>
            <R4>1</R4>
            <R5>2</R5>
            <R6>3</R6>
            <R7>4</R7>
            <R8>5</R8>
            <R9>6</R9>
        </report>
    </reports>
</transmission>
